salesea/__command__.py
salesea/__init__.py
salesea/__main__.py
salesea/app.py
salesea/config.py
salesea/log.py
salesea/nginx.py
salesea/solution.py
salesea/utils.py
salesea-1.0.35.dist-info/METADATA
salesea-1.0.35.dist-info/WHEEL
salesea-1.0.35.dist-info/entry_points.txt
salesea-1.0.35.dist-info/top_level.txt
salesea-1.0.35.dist-info/RECORD
